brew_cleaner/__init__.py
brew_cleaner/main.py
brew_cleaner-0.1.0.dist-info/licenses/LICENSE
brew_cleaner-0.1.0.dist-info/METADATA
brew_cleaner-0.1.0.dist-info/WHEEL
brew_cleaner-0.1.0.dist-info/entry_points.txt
brew_cleaner-0.1.0.dist-info/top_level.txt
brew_cleaner-0.1.0.dist-info/RECORD
