Metadata-Version: 2.4
Name: brew-cleaner
Version: 0.1.0
Summary: A simple, interactive command-line tool to help you clean up your installed Homebrew formulae.
Home-page: 
Author: Harsh
Author-email: 
Classifier: Programming Language :: Python :: 3
Classifier: License :: OSI Approved :: MIT License
Classifier: Operating System :: MacOS
License-File: LICENSE
Requires-Dist: prompt-toolkit==3.0.51
Dynamic: author
Dynamic: classifier
Dynamic: description
Dynamic: description-content-type
Dynamic: license-file
Dynamic: requires-dist
Dynamic: summary
